.coveragerc
CHANGES.rst
CONTRIBUTORS.rst
MANIFEST.in
README.rst
bootstrap.py
buildout.cfg
requirements.txt
setup.py
docs/LICENSE.GPL
docs/LICENSE.txt
docs/mockups/login-mockup.jpg
docs/mockups/signup-mockup.jpg
docs/mockups/trouble-mockup.jpg
src/plone/__init__.py
src/plone.login.egg-info/PKG-INFO
src/plone.login.egg-info/SOURCES.txt
src/plone.login.egg-info/dependency_links.txt
src/plone.login.egg-info/entry_points.txt
src/plone.login.egg-info/namespace_packages.txt
src/plone.login.egg-info/not-zip-safe
src/plone.login.egg-info/requires.txt
src/plone.login.egg-info/top_level.txt
src/plone/login/__init__.py
src/plone/login/configure.zcml
src/plone/login/interfaces.py
src/plone/login/testing.py
src/plone/login/browser/__init__.py
src/plone/login/browser/configure.zcml
src/plone/login/browser/login.py
src/plone/login/browser/login_help.py
src/plone/login/browser/logout.py
src/plone/login/browser/templates/forced_password_change.pt
src/plone/login/browser/templates/initial_login_password_change.pt
src/plone/login/browser/templates/insufficient_privileges.pt
src/plone/login/browser/templates/logged_out.pt
src/plone/login/browser/templates/login.pt
src/plone/login/browser/templates/login_failsafe.pt
src/plone/login/browser/templates/login_help.pt
src/plone/login/browser/templates/subform_render.pt
src/plone/login/locales/plone.pot
src/plone/login/locales/update.sh
src/plone/login/locales/de/LC_MESSAGES/plone.po
src/plone/login/profiles/default/metadata.xml
src/plone/login/profiles/default/skins.xml
src/plone/login/tests/__init__.py
src/plone/login/tests/test_install.py
src/plone/login/tests/test_login_form.py
src/plone/login/tests/test_login_help.py
src/plone/login/tests/test_login_logout.py
src/plone/login/tests/test_redirect_after_login.py
src/plone/login/tests/test_views.py