Metadata-Version: 2.1
Name: plone.login
Version: 1.0rc1
Summary: Plone Login System
Home-page: https://github.com/plone/plone.login
Author: The Plone Foundation
Author-email: plone@plone.org
License: gpl
Keywords: cms plone login security
Platform: UNKNOWN
Classifier: Environment :: Web Environment
Classifier: Operating System :: OS Independent
Classifier: Framework :: Zope2
Classifier: Framework :: Plone
Classifier: Framework :: Plone :: 5.0
Classifier: Framework :: Plone :: 5.1
Classifier: Programming Language :: Python
Classifier: Programming Language :: Python :: 2.7
Classifier: Topic :: Software Development :: Libraries :: Python Modules
Classifier: License :: OSI Approved :: GNU General Public License v2 (GPLv2)
Provides-Extra: test
